Metadata-Version: 1.0
Name: nsq2kafka
Version: 0.0.2
Summary: Reads from NSQ, Publishes to Kafka
Home-page: https://github.com/simplereach/nsq2kafka
Author: Russ Bradberry
Author-email: rbradberry@simplereach.com
License: Apache License 2.0
Keywords: NSQ,Kafka
Platform: UNKNOWN
